Workbook

Sheet Requirements Tracker
A1: Req ID | B1: Module/Menu | C1: Requirement | D1: Requestor | E1: Priority | F1: Status | G1: Owner | H1: Created Date | I1: Target Date | J1: Actual Completion | K1: Remarks
C2: ── CRITICAL BUGS / API FAILURES ──
A3: ESS-001 | B3: HR > ESS > My Portal | C3: ESS Dashboard API returns 404 for admin user — admin has no employee record linked; error message should be user-friendly 'Not an employee' instead of 404 | D3: Mr. Ramamoorthy | E3: High | F3: Fixed | G3: Mrs. Dhanalakshmi | H3: 46184 | I3: 46186 | K3: Bug: essService.getEmployeeByUserId throws NotFoundError → HTTP 404 — no graceful handling
A4: ESS-002 | B4: HR > ESS > My Portal / My Attendance | C4: shiftName always null in attendance summary and dashboard — ess.service.ts does not join with hr.shifts/shift_assignments table | D4: Mr. Ramamoorthy | E4: High | F4: Fixed | G4: Mrs. Dhanalakshmi | H4: 46184 | I4: 46186 | K4: ess.service.ts getMyAttendance + getDashboard — shiftName hardcoded null
A5: ESS-003 | B5: HR > ESS > My Portal | C5: Dashboard KPI tile 'Days Present' shows raw status enum text (e.g. 'PRESENT') instead of days count for the month | D5: Mr. Ramamoorthy | E5: High | F5: Fixed | G5: Mrs. Dhanalakshmi | H5: 46184 | I5: 46186 | K5: portal.tsx line 93 — todayAtt.status rendered as tile value, should show present-days count
A6: ESS-004 | B6: HR > ESS > My Attendance | C6: Attendance today endpoint returns different status enum ('not_punched/checked_in/checked_out') vs attendance list ('PRESENT/ABSENT') — inconsistent contract | D6: Mr. Ramamoorthy | E6: High | F6: Fixed | G6: Mrs. Dhanalakshmi | H6: 46184 | I6: 46186 | K6: ess.controller.ts getMyAttendanceToday vs getMyAttendance — normalise status enums
A7: ESS-005 | B7: HR > ESS > My Portal | C7: Dashboard 'Welcome,' renders blank name — API 404 means data is null so employee.name is never populated | D7: Mr. Ramamoorthy | E7: Medium | F7: Fixed | G7: Mrs. Dhanalakshmi | H7: 46184 | I7: 46186 | K7: portal.tsx line 83 — falls back to empty string when data is null due to 404
C8: ── MISSING FRONTEND FEATURES ──
A9: ESS-006 | B9: HR > ESS > My Leave | C9: No 'Apply Leave' button or dialog on ESS Leave page — employees cannot submit leave requests from self-service portal | D9: Mr. Ramamoorthy | E9: High | F9: Fixed | G9: Mrs. Dhanalakshmi | H9: 46184 | I9: 46186 | K9: leave.tsx has no POST flow; essApi has no applyLeave method; i18n key hr.ess.leave.apply exists but unused
A10: ESS-007 | B10: HR > ESS > My Attendance | C10: No Check-In / Check-Out punch UI on ESS Attendance page — backend POST /hr/ess/attendance/punch API is fully implemented but there is no button on the frontend | D10: Mr. Ramamoorthy | E10: High | F10: Fixed | G10: Mrs. Dhanalakshmi | H10: 46184 | I10: 46186 | K10: attendance.tsx — punch button missing; essApi has no punchAttendance method
A11: ESS-008 | B11: HR > ESS > My Payslips | C11: No payslip download / print option on Payslips page — i18n key hr.ess.payslips.download exists but is not wired up | D11: Mr. Ramamoorthy | E11: High | F11: Fixed | G11: Mrs. Dhanalakshmi | H11: 46184 | I11: 46186 | K11: payslips.tsx — no download action column or button; getPayslipById API exists
A12: ESS-009 | B12: HR > ESS > My Payslips | C12: No payslip detail view / drill-down — clicking a row does nothing; detailed component breakdown (earnings, deductions) not shown | D12: Mr. Ramamoorthy | E12: Medium | F12: Fixed | G12: Mrs. Dhanalakshmi | H12: 46184 | I12: 46186 | K12: payslips.tsx — no row click handler; getPayslipById in essApi unused
A13: ESS-010 | B13: HR > ESS > My Payslips | C13: No year filter UI on Payslips page — backend supports ?year= query param but there is no year picker on the frontend | D13: Mr. Ramamoorthy | E13: Medium | F13: Fixed | G13: Mrs. Dhanalakshmi | H13: 46184 | I13: 46186 | K13: payslips.tsx — year filter missing; backend essService.getMyPayslips supports year param
A14: ESS-011 | B14: HR > ESS > Tax Declaration | C14: Tax Declaration page (/hr/ess/tax) does not exist — referenced in dashboard pendingActions but navigates to a 404 | D14: Mr. Ramamoorthy | E14: High | F14: Fixed | G14: Mrs. Dhanalakshmi | H14: 46184 | I14: 46186 | K14: ess.service.ts line 82 — investment declaration pendingAction links to /hr/ess/tax; page not built
A15: ESS-012 | B15: HR > MSS > Manager Self-Service | C15: MSS (Manager Self-Service) frontend completely missing — backend routes, service, and controller for MSS are fully implemented (team dashboard, team attendance, leave approvals, batch approvals) but no frontend pages exist | D15: Mr. Ramamoorthy | E15: High | F15: Fixed | G15: Mrs. Dhanalakshmi | H15: 46184 | I15: 46186 | K15: mssApi exists in ess-mss.api.ts; mss.controller.ts + mss.service.ts complete; no pages in hr/ess/ for MSS
A16: ESS-013 | B16: HR > ESS > My Profile | C16: Employee photo not displayed on Profile page — photoUrl field is returned by API but not rendered in profile.tsx | D16: Mr. Ramamoorthy | E16: Low | F16: Fixed | G16: Mrs. Dhanalakshmi | H16: 46184 | I16: 46186 | K16: profile.tsx — mapProfileRow returns photoUrl; profile page has no avatar/img element
A17: ESS-014 | B17: HR > ESS > My Profile | C17: No Aadhar number shown in Statutory Details — only PAN and UAN displayed; Aadhar is a mandatory statutory field in Indian payroll | D17: Mr. Ramamoorthy | E17: Medium | F17: Fixed | G17: Mrs. Dhanalakshmi | H17: 46184 | I17: 46186 | K17: ess.service.ts mapProfileRow — aadhar_number column not selected; profile.tsx only shows panNumber + uanNumber
A18: ESS-015 | B18: HR > ESS > My Portal | C18: Leave balance in portal dashboard shows typeCode (e.g., 'CL') not full typeName — poor readability | D18: Mr. Ramamoorthy | E18: Low | F18: Fixed | G18: Mrs. Dhanalakshmi | H18: 46184 | I18: 46186 | K18: portal.tsx line 143 — displays lb.typeCode; should show lb.typeName with typeCode as badge
A19: ESS-016 | B19: HR > ESS > My Leave | C19: Leave balance does not show carry-forward days — carryForward is hardcoded to 0 in service; no carry-forward column in leave balance cards | D19: Mr. Ramamoorthy | E19: Medium | F19: Fixed | G19: Mrs. Dhanalakshmi | H19: 46184 | I19: 46186 | K19: ess.service.ts line 257 — carryForward: 0 hardcoded; hr.leave_credits should track carry-forward
A20: ESS-017 | B20: HR > ESS > My Profile | C20: No 'Raise HR Request' ticketing / service request system — profile page only shows static text 'please raise a request with HR' with no action link | D20: Mr. Ramamoorthy | E20: Medium | F20: Fixed | G20: Mrs. Dhanalakshmi | H20: 46184 | I20: 46186 | K20: profile.tsx line 243 — no navigation or modal for HR service requests
... A22: ESS-019 | B22: HR > ESS > My Portal | C22: No pending approvals / notification count on ESS portal dashboard | D22: Mr. Ramamoorthy | E22: Low | F22: Fixed | G22: Mrs. Dhanalakshmi | H22: 46184 | I22: 46186 | K22: portal.tsx — no pendingActions badge; investment declaration only seasonal; no notification bell
C23: ── VALIDATION GAPS ──
A24: ESS-020 | B24: HR > ESS > My Profile | C24: Profile update: no phone number format validation on frontend (should be 10-digit Indian mobile) | D24: Mr. Ramamoorthy | E24: Medium | F24: Fixed | G24: Mrs. Dhanalakshmi | H24: 46184 | I24: 46186 | K24: profile.tsx handleSave — no Zod/Joi validation; raw string sent to PUT /hr/ess/profile
A25: ESS-021 | B25: HR > ESS > My Profile | C25: Profile update: no email format validation on frontend — invalid email can be submitted | D25: Mr. Ramamoorthy | E25: Medium | F25: Fixed | G25: Mrs. Dhanalakshmi | H25: 46184 | I25: 46186 | K25: profile.tsx — no email regex check before calling essApi.updateMyProfile
A26: ESS-022 | B26: HR > ESS > My Profile | C26: Profile update: no postal code validation (should be 6-digit Indian PIN) | D26: Mr. Ramamoorthy | E26: Low | F26: Fixed | G26: Mrs. Dhanalakshmi | H26: 46184 | I26: 46186 | K26: profile.tsx — postalCode field accepts any string
A27: ESS-023 | B27: HR > ESS > My Profile | C27: Profile update: allows blank/empty strings to overwrite existing values — no required field guard | D27: Mr. Ramamoorthy | E27: Medium | F27: Fixed | G27: Mrs. Dhanalakshmi | H27: 46184 | I27: 46186 | K27: profile.tsx — form submitted even with blank fields; backend updates empty string to DB
A28: ESS-024 | B28: HR > ESS > My Profile | C28: Profile update: no validator on backend (ess.controller.ts updateMyProfile passes req.body directly to service without validation) | D28: Mr. Ramamoorthy | E28: High | F28: Fixed | G28: Mrs. Dhanalakshmi | H28: 46184 | I28: 46186 | K28: ess.controller.ts line 127 — req.body passed raw to essService.updateProfile; no Joi/Zod validator
A29: ESS-025 | B29: HR > ESS > Resign / Separation | C29: Resignation: lastWorkingDay minimum date not calculated from notice period — employee should not be able to set LWD earlier than resignation date + required notice period days | D29: Mr. Ramamoorthy | E29: High | F29: Fixed | G29: Mrs. Dhanalakshmi | H29: 46184 | I29: 46186 | K29: resignation.tsx line 439 — min={form.resignationDate}; should be resignationDate + noticeRequiredDays
A30: ESS-026 | B30: HR > ESS > Resign / Separation | C30: Resignation: no duplicate submission guard — employee can submit another resignation if previous is in APPROVED/NOTICE_PERIOD status (frontend only blocks CANCELLED re-submission) | D30: Mr. Ramamoorthy | E30: High | F30: Fixed | G30: Mrs. Dhanalakshmi | H30: 46184 | I30: 46186 | K30: ess.service.ts submitResignation — no check for existing active resignation before calling separationService.createRequest
A31: ESS-027 | B31: HR > ESS > Resign / Separation | C31: Resignation: no minimum notice period validation on lastWorkingDay — backend separationService.createRequest does not validate LWD against employee's contractual notice period | D31: Mr. Ramamoorthy | E31: High | F31: Fixed | G31: Mrs. Dhanalakshmi | H31: 46184 | I31: 46186 | K31: separation.service.ts createRequest — no notice period validation; employees can bypass contractual notice
A32: ESS-028 | B32: HR > ESS > My Leave | C32: Leave apply (missing feature): when implemented, must validate: (a) min 1 day, (b) from ≤ to date, (c) no overlap with existing approved leave, (d) no leave on weekends/holidays, (e) half-day leave validation | D32: Mr. Ramamoorthy | E32: High | F32: Fixed | G32: Mrs. Dhanalakshmi | H32: 46184 | I32: 46186 | K32: Pre-requisite for ESS-006 — leave apply flow validation requirements
A33: ESS-029 | B33: HR > ESS > My Attendance | C33: Attendance punch (missing feature): when implemented, must validate: (a) no double check-in, (b) check-out only after check-in, (c) geo-location coordinates, (d) grace period for late marking | D33: Mr. Ramamoorthy | E33: Medium | F33: Fixed | G33: Mrs. Dhanalakshmi | H33: 46184 | I33: 46186 | K33: Pre-requisite for ESS-007 — attendance punch validation requirements
C34: ── i18n HARDCODED STRINGS ──
A35: ESS-030 | B35: HR > ESS > My Portal | C35: portal.tsx: 'Quick Links', 'Pending Actions', 'Shift' KPI title, 'Month', 'Gross Earnings', 'Deductions', 'Net Pay', 'Credit Date', 'No payslip data available' — all hardcoded | D35: Mr. Ramamoorthy | E35: Medium | F35: Fixed | G35: Mrs. Dhanalakshmi | H35: 46184 | I35: 46186 | K35: portal.tsx lines 98, 217, 179, 200, 203, 205 — ~9 hardcoded strings
A36: ESS-031 | B36: HR > ESS > My Attendance | C36: attendance.tsx: 'View your attendance records by month', 'Total Days', all column headers (Date/Status/Shift/Check In/Check Out/Hours/Remarks), search placeholders, empty messages — hardcoded | D36: Mr. Ramamoorthy | E36: Medium | F36: Fixed | G36: Mrs. Dhanalakshmi | H36: 46184 | I36: 46186 | K36: attendance.tsx — ~12 hardcoded strings
A37: ESS-032 | B37: HR > ESS > My Leave | C37: leave.tsx: 'Active / Pending', 'History' tabs, 'Leaves Taken', 'Pending' KPI labels, all column headers (Type/From/To/Days/Status/Reason/Applied), search placeholders, empty messages, subtitle — hardcoded | D37: Mr. Ramamoorthy | E37: Medium | F37: Fixed | G37: Mrs. Dhanalakshmi | H37: 46184 | I37: 46186 | K37: leave.tsx — ~15 hardcoded strings
A38: ESS-033 | B38: HR > ESS > My Payslips | C38: payslips.tsx: 'Pay Period', 'Gross Earnings', 'Deductions', 'Net Pay', 'Credit Date', 'Status' column headers, search placeholder, 'view your monthly salary slips' subtitle, 'No payslips available' — hardcoded | D38: Mr. Ramamoorthy | E38: Medium | F38: Fixed | G38: Mrs. Dhanalakshmi | H38: 46184 | I38: 46186 | K38: payslips.tsx — ~9 hardcoded strings
A39: ESS-034 | B39: HR > ESS > My Profile | C39: profile.tsx: all card section titles ('Personal Information', 'Employment Details', 'Address', 'Emergency Contact', 'Statutory Details'), all field labels, 'Cancel'/'Save' buttons, 'Profile not available' message, statutory note — hardcoded | D39: Mr. Ramamoorthy | E39: Medium | F39: Fixed | G39: Mrs. Dhanalakshmi | H39: 46184 | I39: 46186 | K39: profile.tsx — ~35+ hardcoded strings; largest i18n debt in ESS
A40: ESS-035 | B40: HR > ESS > Resign / Separation | C40: resignation.tsx: REASON_CATEGORIES labels array (8 labels) hardcoded in TS constant — should come from i18n so Hindi/Tamil translations work | D40: Mr. Ramamoorthy | E40: Low | F40: Fixed | G40: Mrs. Dhanalakshmi | H40: 46184 | I40: 46186 | K40: resignation.tsx lines 32-40 — REASON_CATEGORIES not internationalised
A41: ESS-036 | B41: HR > ESS > All ESS Pages | C41: All ESS pages: error toast messages hardcoded in English ('Failed to load ESS dashboard', 'Failed to load leave data', 'Failed to load attendance', 'Failed to load profile', 'Failed to load payslips') — not i18n'd | D41: Mr. Ramamoorthy | E41: Low | F41: Fixed | G41: Mrs. Dhanalakshmi | H41: 46184 | I41: 46186 | K41: portal/leave/attendance/profile/payslips .tsx catch blocks — error strings hardcoded
C42: ── UX / ERP STANDARDS GAPS ──
A43: ESS-037 | B43: HR > ESS > My Payslips | C43: Payslips page: credit date displayed with raw '|| —' fallback instead of formatDateDMY — breaks date locale consistency | D43: Mr. Ramamoorthy | E43: Low | F43: Fixed | G43: Mrs. Dhanalakshmi | H43: 46184 | I43: 46186 | K43: payslips.tsx line 117 — accessor: (row) => row.creditDate || '—' should use formatDateDMY
A44: ESS-038 | B44: HR > ESS > My Attendance | C44: Attendance page: uses basic HTML <input type='month'> instead of locale-aware month picker — inconsistent with other HR pages that use MonthPicker component | D44: Mr. Ramamoorthy | E44: Low | F44: Fixed | G44: Mrs. Dhanalakshmi | H44: 46184 | I44: 46186 | K44: attendance.tsx line 198-205 — <Input type='month'>; other HR pages (overtime) use locale-aware MonthPicker
A45: ESS-039 | B45: HR > ESS > My Leave | C45: Leave balance carry-forward not visible anywhere in ESS — no dedicated 'Carried Forward' row; employees cannot see how many days were carried over from previous year | D45: Mr. Ramamoorthy | E45: Medium | F45: Fixed | G45: Mrs. Dhanalakshmi | H45: 46184 | I45: 46186 | K45: leave.tsx LeaveBalance cards have no carry-forward display; service hardcodes carryForward: 0
A46: ESS-040 | B46: HR > ESS > Resign / Separation | C46: Resignation page: no upload document option for resignation letter or supporting documents | D46: Mr. Ramamoorthy | E46: Low | F46: Fixed | G46: Mrs. Dhanalakshmi | H46: 46184 | I46: 46186 | K46: resignation.tsx — no file attachment; separation.types.ts has no document_url field
A47: ESS-041 | B47: HR > ESS > My Profile | C47: ESS portal: no self-service document upload for personal documents (address proof, bank change form, ID update) — only mentioned as static text in profile page | D47: Mr. Ramamoorthy | E47: Medium | F47: Fixed | G47: Mrs. Dhanalakshmi | H47: 46184 | I47: 46186 | K47: profile.tsx line 243 — static note only; no upload endpoint or component
C48: ── RBAC / PERMISSIONS ── | I48: 46186
A49: ESS-042 | B49: HR > ESS > All ESS Routes (Backend) | C49: ESS routes: all write operations (profile update, resignation submit/withdraw, attendance punch) use authorize('hr.ess.read') — should use hr.ess.write for mutation endpoints | D49: Mr. Ramamoorthy | E49: High | F49: Fixed | G49: Mrs. Dhanalakshmi | H49: 46184 | I49: 46186 | K49: ess-mss.routes.ts line 10 — single router.use(authorize('hr.ess.read')) covers PUT/POST/DELETE; mismatch
A50: ESS-043 | B50: HR > ESS > My Portal | C50: Admin user accessing ESS pages sees hard crash ('Failed to load ESS dashboard') — no graceful 'ESS is for employees' banner or redirect for users without an employee record | D50: Mr. Ramamoorthy | E50: Medium | F50: Fixed | G50: Mrs. Dhanalakshmi | H50: 46184 | I50: 46186 | K50: portal.tsx — should detect 404/no-employee and show informational state instead of error toast
A51: ESS-044 | B51: HR > MSS > All MSS Routes (Backend) | C51: MSS routes authorise with hr.ess.read instead of a distinct hr.mss.read permission — managers and employees share one permission; cannot restrict MSS to managers only | D51: Mr. Ramamoorthy | E51: Medium | F51: Fixed | G51: Mrs. Dhanalakshmi | H51: 46184 | I51: 46186 | K51: ess-mss.routes.ts — MSS routes should use authorize('hr.mss.read') or role-based guard
A52: SAL-001 | B52: Sales > Orders > Line Items Step | C52: Line Items table redesign â€” removed GST% column (now 9 cols); renamed Amount to Taxable Value; added separate IGST and CGST+SGST tax amount columns; footer shows IGST @ 18% and CGST @ 9% + SGST @ 9% labels; Subtotal footer reflects post-discount lineItemTaxable value | D52: Mr.Ragesh | E52: Medium | F52: Fixed | G52: Gowtham | H52: 46184 | I52: 46184 | J52: 46184
A53: SAL-002 | B53: Sales > Orders > Order Items Tab | C53: Order Items tab updated â€” added Discount column showing total amount and per-MT rate; Amount column now shows post-discount taxable value; Tax Breakdown card redesigned with taxableBase including freight/packing/insurance/otherCharges (aligns with OrderTotalsSummary) | D53: Mr.Ragesh | E53: Medium | F53: Fixed | G53: Gowtham | H53: 46184 | I53: 46184 | J53: 46184
A54: SAL-003 | B54: Sales > Orders > Backend Schema | C54: Added discount_type (flat|percent) column to sales_order_items â€” V7.85 migration adds column; V7.86 backfills 8 existing rows as flat; is_deduction flag added to price_adjustments (users enter positive amount and choose discount/surcharge direction); commission agent currency fixed; payment terms overwrite on edit fixed | D54: Mr.Ragesh | E54: High | F54: Fixed | G54: Gowtham | H54: 46184 | I54: 46184 | J54: 46184
A55: SAL-004 | B55: Sales > Orders > Order Header Step | C55: Export order destination country auto-select implemented â€” defaults to customer incorporationCountry; overrides with ship-to address country when different; fixed useEffect variable ordering bug in OrderHeaderStepForm | D55: Mr.Ragesh | E55: Medium | F55: Fixed | G55: Gowtham | H55: 46184 | I55: 46184 | J55: 46184
A56: INV-001 | B56: Sales > Invoice | C56: Fixed flat discount display on invoice â€” was incorrectly showing % symbol; now shows Rs/MT; gross minus discount minus net breakdown added to Taxes and Financial Summary; total discount in Rs shown in Review; values rounded to 2 decimal places | D56: Mr.Ragesh | E56: High | F56: Fixed | G56: Gowtham | H56: 46184 | I56: 46184 | J56: 46184
A57: INV-002 | B57: Sales > Invoice | C57: Added discountType field to invoice types/validator/service and InvoiceCreateEditPage.tsx to support flat Rs/MT discounts inherited from Sales Orders; backfilled 8 existing invoice items with discount_type=flat via V7.86 migration | D57: Mr.Ragesh | E57: Medium | F57: Fixed | G57: Gowtham | H57: 46184 | I57: 46184 | J57: 46184
A58: PAR-001 | B58: Parties > Address Management | C58: Fixed address display in Parties module â€” state and country fields were showing raw lookup codes (e.g. 33 and IN) instead of resolved names (Tamil Nadu and India); fixed in AddressesStep and PartyDetailPage using usePartyLookups hook | D58: Mr.Ragesh | E58: High | F58: Fixed | G58: Gowtham | H58: 46184 | I58: 46184 | J58: 46184
A59: PAR-002 | B59: Parties > Address Dialog | C59: Fixed international address autofill in AddressDialog â€” added alphanumeric postal code validation for non-India addresses (was failing Indian PIN 6-digit rule); state/province field changed to free-text input for international addresses; integrated zippopotam.us API for international postal code auto-lookup | D59: Mr.Ragesh | E59: Medium | F59: Fixed | G59: Gowtham | H59: 46184 | I59: 46184 | J59: 46184
A60: SAL-012 | B60: Orders -> View Order | C60: Pricelist i use currecy in USD ,same price list i used in order but in order view show INR currency | D60: Mr.Ragesh | E60: High | F60: Fixed | G60: Gowtham | H60: 46185 | I60: 46185
A61: INV-003 | B61: Invoice | C61: Pricelist i use currecy in USD ,order converted to invoice but in invoice show INR currency | D61: Mr.Ragesh | E61: High | F61: Fixed | G61: Gowtham | H61: 46185 | I61: 46185
A62: INV-004 | B62: Invoice | C62: Order type is Export and GST Supply Sub-Type is EXPWOP means no gst ,so no gst calculation happen in order and invoice stage | D62: Mr.Ragesh | E62: Medium | F62: Fixed | G62: Gowtham | H62: 46185 | I62: 46185
A63: INV-005 | B63: Invoice | C63: Have to issue Commercial Invoice in USD (two invoice need USD for party and INR - this for eway bill) | D63: Mr.Ragesh | E63: Low | F63: Fixed | G63: Gowtham | H63: 46185
A64: INV-006 | B64: Invoice | C64: Also for the purpose of E Invoice / Eway Bill - INR invoice - Option to add Exchange rate during invoicing time | D64: Mr.Ragesh | E64: Medium | F64: Fixed | G64: Gowtham | H64: 46185 | I64: 46186
A65: DPO-001 | B65: Dispatch order | C65: Export Loading Details provide for edit dispatch order page | D65: Mr.Ragesh | E65: Medium | F65: Fixed | G65: Gowtham | H65: 46185 | I65: 46185
A66: SAL-005 | B66: Sales > Orders > Create Form > Address Preview | C66: Fixed state code display in billing and shipping address preview — state_province column stores numeric GST code (e.g. 32 for Kerala); formatFullAddress now resolves both gstStateCode and addr.state via useIndianStates lookup and renders stateName (e.g. Kerala) instead of raw code. resolveStateName helper added to ReviewSubmitStepForm for the same fix on Review & Submit step. | D66: Mr. Ragesh | E66: Medium | F66: Fixed | G66: Thiravidam | H66: 46185 | I66: 46185 | J66: 46185 | K66: Files: useIndianStates.ts, OrderHeaderStepForm.tsx, ReviewSubmitStepForm.tsx. Issue #25.
A67: SAL-006 | B67: Sales > Orders > Create Form > Address Preview | C67: Added GSTIN display after billing and shipping address preview blocks — buyerGstin (auto-populated from customer taxIdentificationNumber) now shown as "GST: <number>" below each address block on Order Header step and Review & Submit step. | D67: Mr. Ragesh | E67: Medium | F67: Fixed | G67: Thiravidam | H67: 46185 | I67: 46185 | J67: 46185 | K67: Files: OrderHeaderStepForm.tsx, ReviewSubmitStepForm.tsx. Issue #26.
A68: SAL-007 | B68: Sales > Orders > Create Form > Order Header Step | C68: Order Header step UI reorganization — (1) Removed duplicate GST/Tax summary row (Buyer GSTIN, Place of Supply, Intra/Inter-State badge) from address section. (2) Moved Partner Details (Ship-to / Payer override) to appear after Ship-to Address, before Payment Terms. (3) Moved Reverse Charge field to appear after PO Date field inside Card 1. (4) Hidden Addresses card (Card 2) entirely as its fields are covered by Bill-to / Ship-to blocks above. | D68: Mr. Ragesh | E68: Low | F68: Fixed | G68: Thiravidam | H68: 46185 | I68: 46185 | J68: 46185 | K68: File: OrderHeaderStepForm.tsx. Merge commit: 98dadad22. Issue #27.
A69: SAL-008 | B69: Sales > Orders > Create Form > Billing Address | C69: Filter billing address dropdown to show only BILLING and REGISTERED address types — dropdown was showing all party address types (including SHIPPING, WAREHOUSE, BRANCH, OTHER). Auto-select on customer change also restricted to same types with null guard to avoid selecting a non-billing address by default. | D69: Mr. Ragesh | E69: Medium | F69: Fixed | G69: Thiravidam | H69: 46185 | I69: 46185 | J69: 46185 | K69: File: OrderHeaderStepForm.tsx. Issue #28. Commit: b64b0ed08
A70: SAL-009 | B70: Sales > Orders > Price List > Rule Matching | C70: Price rule matching must prioritize form-specific rules over any-form rules — when product form is Reel, apply the Reel rule first; when product form is Sheet, apply the Sheet rule first. Fall back to form=Any rules only when no form-specific rule exists. Two-pass matching implemented: Pass 1 exact form match, Pass 2 any-form fallback. | D70: Mr. Ragesh | E70: High | F70: Fixed | G70: Thiravidam | H70: 46185 | I70: 46185 | J70: 46185 | K70: File: price-circular.service.ts. Issue #29. Commit: a8a75080c
A71: SAL-010 | B71: Sales > Orders > Create Form > Discount Remarks | C71: Add Discount Remarks section between Line Items and Additional Charges tabs — when a price circular discount is applied and user reduces or removes it, a reason must be provided. Section shows summary of circular vs applied discount per item and a single order-level remark field (required if any discount reduced, optional otherwise). discount_remark stored in order payload. | D71: Mr. Ragesh | E71: Medium | F71: Fixed | G71: Thiravidam | H71: 46185 | I71: 46185 | J71: 46185 | K71: Files: DiscountRemarksStepForm.tsx (new), OrderCreateEditPage.tsx, LineItemsStepForm.tsx, order-form.types.ts. Issue #30. Commit: 289a4f533
A72: SAL-011 | B72: Sales > Orders > Line Items > Discount Breakdown | C72: Show per-adjustment discount breakdown in line items table — when a price circular has multiple adjustments (e.g. dd=26/MT, AD=50/MT), display each adjustment type on its own row in the Discount column with an individually editable value. Deductions shown with − prefix, surcharges with + prefix. Net discount total shown as footer. Falls back to single input when no circular adjustments. | D72: Mr. Ragesh | E72: Medium | F72: Fixed | G72: Thiravidam | H72: 46185 | I72: 46185 | J72: 46185 | K72: Files: LineItemsStepForm.tsx, order-form.types.ts (ICircularAdjustmentLine). Issue #31. Commit: 259e6e495
A73: HR-SH-001 | B73: HR>Shift Management>Shift Roster | C73: Roster Shift Details Should be in Matrix Format like Bulk Atttendance Page | D73: Mr.Ramamoorthy | E73: Medium | F73: Open | G73: Dhanalakshmi | H73: 46185 | I73: 46186
A74: HR-SH-002 | B74: HR>Shift Management>Shift Roster | C74: Department wise Roster and general Roster Option | D74: Mr.Ramamoorthy | E74: High | F74: Open | G74: Dhanalakshmi | H74: 46185 | I74: 46189
A75: HR-PR-001 | B75: HR>Payroll | C75: financial year annual bonus calculation State-Specific PT & Bonus Handling-financial year annual bonus calculation | D75: Mr.Ramamoorthy | E75: High | F75: Open | G75: Dhanalakshmi | H75: 46185 | I75: 46218
A76: HR-SE-001 | B76: HR>Separation&Exit | C76: Notice Period Policy Option | D76: Mr.Ramamoorthy | E76: High | F76: Open | G76: Dhanalakshmi | H76: 46185 | I76: 46187
A77: HR-SH-003 | B77: HR>Shift Management>Shift Roster | C77: No roster template cloning-Users creating a 3-week ROTATING template for Department B that is similar to Department A's template must re-enter all rows. No "clone template" endpoint exists. | D77: Mr.Ramamoorthy | E77: High | F77: Fixed | G77: Dhanalakshmi | H77: 46185 | I77: 46187
A78: HR-SH-004 | B78: HR>Shift Management>Shift Roster | C78: No individual assignment override from matrix view Clicking a cell in the matrix opens assign/edit dialog, but saving creates a separate assignment — it doesn't modify the roster template. There's no way to mark "this employee is exception to the template on this date" | D78: Mr.Ramamoorthy | E78: High | F78: Fixed | G78: Dhanalakshmi | H78: 46185 | I78: 46187
A79: HR-SH-005 | B79: HR>Shift Management>Shift Roster | C79: No roster "apply to date range" rollback clear_existing is destructive with no undo. If the generate run fails mid-way (e.g. DB error at employee 40/50), the first 39 employees are generated, the rest are cleared and not regenerated. No transaction wraps the entire generate loop. | D79: Mr.Ramamoorthy | E79: High | F79: Fixed | G79: Dhanalakshmi | H79: 46185 | I79: 46187
A80: DPO-003 | B80: Dispatch Order | C80: Driver details warning banner on dispatch order detail page | D80: Mr. Ragesh | E80: Medium | F80: Fixed | G80: Gowtham | H80: 46186 | I80: 46186 | J80: 46186 | K80: Warning shown on DRAFT orders missing vehicle number, driver name, or phone
A81: DPO-004 | B81: Dispatch Order | C81: Filter available orders list to stock-allocated orders only in create wizard | D81: Mr. Ragesh | E81: High | F81: Fixed | G81: Gowtham | H81: 46186 | I81: 46186 | J81: 46186 | K81: Only orders with reels assigned / approved FG entries / bundles shown; non-allocated orders excluded
A82: INV-007 | B82: Invoices | C82: Auto-set EXPORT_INVOICE type when creating invoice from export dispatch order | D82: Mr. Ragesh | E82: Medium | F82: Fixed | G82: Gowtham | H82: 46186 | I82: 46186 | J82: 46186 | K82: Invoice type automatically set to EXPORT_INVOICE when sourced from an export dispatch order

Sheet Issue Tracker
A1: Issue ID | B1: Module | C1: Issue Description | D1: Severity | E1: Reported By | F1: Owner | G1: Status | H1: Open Date | I1: Due Date | J1: Days Open | K1: Resolution
A2: 1 | B2: Procurement > Supplier Quotations | C2: Procurement > Supplier Quotations > List — Quotation list shows wrong total amount (SQ-2606-0006: ₹14,052 vs correct ₹13,452). updateQuotation was replacing lines without recalculating header totals. | D2: medium | E2: Manjunath | F2: Thiravidam | G2: completed | H2: 46184 | I2: 46184 | J2: 0 | K2: Fixed: Added header total recalculation (subtotal, tax_amount, total_amount) after line replacement in supplier-quotation.service.ts
A3: 2 | B3: Procurement > Supplier Quotations | C3: Procurement > Supplier Quotations > List — Import quotation (SQ-2606-0002) showing foreign currency amount ₹4,59,728 instead of landed cost INR ₹4,53,52,520. List page was displaying USD total_amount as INR. | D3: high | E3: Manjunath | F3: Thiravidam | G3: completed | H3: 46184 | I3: 46184 | J3: 0 | K3: Fixed: List page now renders landedCostInr for IMPORT supplier type instead of total_amount
A4: 3 | B4: Procurement > Purchase Requisitions | C4: Procurement > Purchase Requisitions — Line item Net Total shows tax-inclusive value (₹1,050) in line tab but Review page and list show pre-tax value (₹1,000). Estimated amount also excluded tax. | D4: medium | E4: Manjunath | F4: Thiravidam | G4: completed | H4: 46184 | I4: 46184 | J4: 0 | K4: Fixed: Backend calculateLineAmounts uses netAmt (post-discount+tax) for estimatedAmount; FE ReviewStep total now includes discount & tax
A5: 4 | B5: Procurement > Purchase Orders | C5: Procurement > Purchase Orders > List — Total Amount column showing ₹0 for all POs. | D5: medium | E5: Thiravidam | F5: Thiravidam | G5: completed | H5: 46184 | I5: 46184 | J5: 0 | K5: Fixed: PO list column accessor changed from netAmount (non-existent) to totalAmount
A6: 5 | B6: Procurement > Purchase Orders | C6: Procurement > Purchase Orders — Converting quotation to PO results in tax showing zero in PO view and edit form. | D6: high | E6: Manjunath | F6: Thiravidam | G6: completed | H6: 46184 | I6: 46184 | J6: 0 | K6: Fixed: Line mapper corrected api.tax_rate → api.igst_percent; header mapper corrected api.total_tax_amount → api.total_tax; form fallback no longer overrides explicit 0% tax with 18%
A7: 6 | B7: Master Data > Supplier Master | C7: Master Data > Supplier Master > Certifications — 500 Internal Server Error when saving certification. DB check constraint chk_certification_type rejected values sent by frontend. | D7: high | E7: Manjunath | F7: Thiravidam | G7: completed | H7: 46184 | I7: 46184 | J7: 0 | K7: Fixed: Aligned all three layers — DB constraint codes (ISO_9001, ISO_14001, etc.), backend validator enum, and frontend dropdown options
A8: 7 | B8: Production > Material Requisitions | C8: Production > Material Requisitions — After clicking Post Goods Issue, Lines tab shows Issued = 0 for all lines. MR stuck in APPROVED when materials were already issued via Work Order page. | D8: high | E8: Manjunath | F8: Thiravidam | G8: completed | H8: 46184 | I8: 46184 | J8: 0 | K8: Fixed: issue() now checks for pending WO materials first; if already issued via WO, reuses existing GI doc and updates MR lines from wo_materials.issued_quantity via JOIN
A9: 8 | B9: Production > Material Requisitions | C9: Production > Material Requisitions — Issuing material via Work Order material dialog does not update quantity_issued on MR requisition lines. MR detail Lines tab always shows Issued = 0. | D9: medium | E9: Manjunath | F9: Thiravidam | G9: completed | H9: 46184 | I9: 46184 | J9: 0 | K9: Fixed: workOrderService.issueMaterial() and postGoodsIssue() now sync wo_material_requisition_lines.issued_quantity after updating wo_materials
A10: 9 | B10: Inventory > Material Requests | C10: Inventory > Material Requests > Lines tab — Lines tab shows quantity_issued = 0 even when material issues are in Approved status. applyIssuance was only called on postIssue (Post to Stock), not on approveIssue. Fixed by syncing MR line quantities at approve time, guarding postIssue against double-counting via delta, and reversing on cancelIssue. | D10: high | E10: Thiravidam | F10: Thiravidam | G10: completed | H10: 46184 | I10: 46184 | J10: 0 | K10: Fixed in material-issue.service.ts: sync MR lines on approveIssue (final level), delta guard in postIssue, reverseIssuance in cancelIssue. DB backfill: 5 lines, 2 MR headers updated.
A11: 10 | B11: Master Data > Business Partners | C11: Master Data > Business Partners — Address display and edit page showing raw state/country codes (e.g. "TN", "IN") instead of resolved names (e.g. "Tamil Nadu", "India"). | D11: medium | E11: Thiravidam | F11: Thiravidam | G11: completed | H11: 46184 | I11: 46184 | J11: 0 | K11: Commits: 41fd891ca, a4c79605b
A12: 11 | B12: Procurement > Supplier Quotations | C12: Procurement > Supplier Quotations > List — Total amount shown without discount. Per-line discount_amount was stored on lines but never rolled up to header discount_amount, so total_amount = subtotal + tax instead of subtotal - discount + tax. | D12: high | E12: Thiravidam | F12: Thiravidam | G12: completed | H12: 46184 | I12: 46184 | J12: 0 | K12: Fixed createQuotation and updateQuotation in supplier-quotation.service.ts to accumulate lineDiscountTotal in loop; Migration V7.99 backfills existing records. Commit: 2dcbdd17f
A13: 12 | B13: Procurement > Supplier Quotations | C13: Procurement > Supplier Quotations > List — Import quotation landed cost showing wrong value. clearing_forwarding and local_transport are per-unit INR values but landed_cost_inr was stored without multiplying by quantity, understating the landed cost. | D13: medium | E13: Thiravidam | F13: Thiravidam | G13: completed | H13: 46184 | I13: 46184 | J13: 0 | K13: Migration V7.98 recalculates line and header landed_cost_inr using cf×qty + lt×qty formula. 33 lines and 27 headers corrected. Commit: d241c3af9
... A15: 14 | B15: Procurement > Supplier Quotations | C15: Procurement > Supplier Quotations > Comparison — Quotation comparison page had broken visibility in dark mode. All card headers, KPI stat cards, supplier quote cards, status chips, alert banners, split-award/PO panels, and inline badges used hardcoded light-mode background classes (bg-white, bg-gray-*, bg-blue-50, etc.) with no dark: variants. | D15: medium | E15: Ram Vicky | F15: Thiravidam | G15: Fixed | H15: 46185 | I15: 46185 | J15: 0 | K15: Fixed: Added dark: variants for all hardcoded light-mode backgrounds in comparative-analysis.tsx (92 changes, 48 insertions). Commit: 7e56ec312
A16: 15 | B16: Shift Roster | C16: Shift Roster>Issue: MONTHLY and CUSTOM patterns do nothing special Where: generateRoster Detail: Both are treated identically to WEEKLY (only day_of_week match). date_sequence column exists in DB and types but is never read during generation. MONTHLY should match by day-of-month (1–31), CUSTOM by explicit date. Currently useless pattern types. | D16: medium | E16: Dhanalakshmi | F16: Dhanalakshmi | G16: Fixed | H16: 46185 | I16: 46185 | J16: =IF(H16="","",TODAY()-H16) -> 2
A17: 16 | B17: Shift Roster | C17: Error messages embed raw UUIDs, not employee codes-Every error entry says "abc-123-uuid on 2026-06-14: approved leave exists". Users cannot read these in the UI. Should be "EMP-00012 on 14-Jun-2026: ...". Employee code is not fetched in the employee list query. | D17: medium | E17: Dhanalakshmi | F17: Dhanalakshmi | G17: Fixed | H17: 46185 | I17: 46185 | J17: =IF(H17="","",TODAY()-H17) -> 2
A18: 17 | B18: Shift Roster | C18: For each employee × each date × shift: 4 sequential DB queries (existing check, leave check, holiday check, overlap check, rest check). A 30-day roster for 50 employees = up to 6,000 sequential DB round-trips. Will time out or severely degrade for large companies. | D18: medium | E18: Dhanalakshmi | F18: Dhanalakshmi | G18: Fixed | H18: 46185 | I18: 46185 | J18: =IF(H18="","",TODAY()-H18) -> 2
A19: 18 | B19: Shift Roster | C19: Holiday query does company_id = $2 OR company_id IS NULL but ignores plant_id-scoped | D19: medium | E19: Dhanalakshmi | F19: Dhanalakshmi | G19: Fixed | H19: 46185 | I19: 46185 | J19: =IF(H19="","",TODAY()-H19) -> 2
A20: 19 | B20: Shift Roster | C20: holidays. An employee in Plant B will have Plant A's holidays applied (or vice-versa). | D20: medium | E20: Dhanalakshmi | F20: Dhanalakshmi | G20: Fixed | H20: 46185 | I20: 46185 | J20: =IF(H20="","",TODAY()-H20) -> 2
A21: 20 | B21: Shift Roster | C21: Query does start_date >= $2 AND start_date <= $3, so a permanent assignment | D21: medium | E21: Dhanalakshmi | F21: Dhanalakshmi | G21: Fixed | H21: 46185 | I21: 46185 | J21: =IF(H21="","",TODAY()-H21) -> 2
A22: 21 | B22: Shift Roster | C22: (start=2026-01-01, end=NULL) is invisible when querying 2026-06-01 to 2026-06-30 unless its | D22: medium | E22: Dhanalakshmi | F22: Dhanalakshmi | G22: Fixed | H22: 46185 | I22: 46185 | J22: =IF(H22="","",TODAY()-H22) -> 2
A23: 22 | B23: Shift Roster | C23: start_date falls in that range. Should use overlap: start_date <= $3 AND (end_date IS NULL OR | D23: medium | E23: Dhanalakshmi | F23: Dhanalakshmi | G23: Fixed | H23: 46185 | I23: 46185 | J23: =IF(H23="","",TODAY()-H23) -> 2
A24: 23 | B24: Shift Roster | C24: end_date >= $2). | D24: medium | E24: Dhanalakshmi | F24: Dhanalakshmi | G24: Fixed | H24: 46185 | I24: 46185 | J24: =IF(H24="","",TODAY()-H24) -> 2
A25: 24 | B25: Shift Roster | C25: The in-memory weeklyAssigned map only tracks assignments created during this run. If an employee already has 5 assignments from a previous run, the counter starts at 0 and allows 6 more. Must pre-seed from DB. | D25: medium | E25: Dhanalakshmi | F25: Dhanalakshmi | G25: Fixed | H25: 46185 | I25: 46185 | J25: =IF(H25="","",TODAY()-H25) -> 2
A26: 25 | B26: Shift Roster | C26: DAY_CYCLE skips check for empOffDays — actually it does check, but dayCycleShiftForDate still returns a shift even on a weekly off day. The off-day skip happens before dayCycleShiftForDate is called, so it should work — but if cycle_reference_date is a Sunday and Sunday is off, position still advances, causing a permanent 1-day drift in the rotation.the cycle | D26: medium | E26: Dhanalakshmi | F26: Dhanalakshmi | G26: Fixed | H26: 46185 | I26: 46185 | J26: =IF(H26="","",TODAY()-H26) -> 2
A27: 26 | B27: Shift Roster | C27: Delete template doesn't check for active generated assignments.deleteRosterTemplate Detail: Hard-deletes the template row with no guard. If employees have active assignments generated from this template, the assignments remain (no roster_template_id FK on hift_assignments) at the template is gone — no audit trail of what generated the assignments. | D27: medium | E27: Dhanalakshmi | F27: Dhanalakshmi | G27: Fixed | H27: 46185 | I27: 46185 | J27: =IF(H27="","",TODAY()-H27) -> 2
A28: 27 | B28: Shift Roster | C28: available_capacity returns minimum_staffing, not maximum.now reads minimum_staffing from production.shifts. But minimum_staffing is the required minimum, not the maximum capacity. These are different concepts. Returning minimum as "available capacity" is semantically wrong — it should be max headcount minus current assigned. | D28: medium | E28: Dhanalakshmi | F28: Dhanalakshmi | G28: Fixed | H28: 46185 | I28: 46185 | J28: =IF(H28="","",TODAY()-H28) -> 2
A29: 28 | B29: Shift Roster | C29: Sales > Sales Orders > Create Form > Bill to Customer — Customer dropdown only showed party name with no code. Users could not distinguish customers with similar names. Search only matched on name. | D29: low | E29: Ragesh | F29: Thiravidam | G29: Fixed | H29: 46186 | I29: 46186 | J29: 0 | K29: Fixed: fetchCustomers now maps partyCode → code. SelectItem renders as "code - name". filteredCustomers search covers both name and code. Placeholder updated to "Search by name or code…". Commit: b0b164838
A30: 29 | B30: Sales > Sales Orders | C30: Sales > Sales Orders > Line Items > Product Search — Newly created products not appearing immediately in the product search dropdown. Browse list used a one-time fetch flag that never reset, so products created after the first focus were invisible until page refresh. | D30: medium | E30: Ragesh | F30: Thiravidam | G30: Fixed | H30: 46186 | I30: 46186 | J30: 0 | K30: Fixed: Added 30s stale TTL to browse list cache (browseFetchedAtRef) — re-fetches on focus after 30s so newly created products appear immediately. Also cleared stale full-search results in performAutocomplete to prevent old results hiding fresh suggestions. Commits: c286901e4
A31: 30 | B31: Sales & Distribution | C31: Sales & Distribution | D31: medium | E31: Manjunath | F31: Gowtham | G31: Fixed | H31: 46186 | I31: 46186 | J31: 1 | K31: give an waring message like please enter driver details to enable start loading option
A32: 31 | B32: Sales & Distribution | C32: Sales & Distribution >invoicing >sales invoices> Generate from so -In sales invoices ,generate from SO ,the text are not visible in the dark theme | D32: high | E32: Kalatheeswaran | F32: Gowtham | G32: Unfixed | H32: 46186 | I32: 46186 | J32: =IF(H32="","",TODAY()-H32) -> 1
A33: 32 | B33: Sales > Sales Orders | C33: Sales > Sales Orders > Line Items > Product Search — Product search was showing all product types (raw material, semi-finished, consumable, etc.). Sales orders should only list Finished Goods products. | D33: medium | E33: Ragesh | F33: Thiravidam | G33: Fixed | H33: 46186 | I33: 46186 | J33: 0 | K33: Fixed: Added productType="finished_goods" to both ProductAutocomplete instances in LineItemsStepForm — filters browse list and autocomplete/search API to FG only. Commit: df4054d3b
A34: 33 | B34: Sales > Sales Orders | C34: Sales > Sales Orders > Bill to Customer — Standard order type was showing only DOMESTIC-typed customers, excluding dealers and null-type customers. Export order type should show only EXPORT customers; all other order types should show all customers except EXPORT. | D34: medium | E34: Ragesh | F34: Thiravidam | G34: Fixed | H34: 46186 | I34: 46186 | J34: 0 | K34: Fixed: fetchCustomers now fetches all customers for non-export orders and filters EXPORT type client-side (case insensitive). Export orders use API-level customerType=EXPORT filter. Info text updated to "all non-export customers". Commit: 517d10cff
A35: 34 | B35: Sales > Sales Orders | C35: Sales > Sales Orders > Round Off — Round off toggle was disabled by default on new sales orders, requiring users to manually enable it every time. | D35: low | E35: Ragesh | F35: Thiravidam | G35: Fixed | H35: 46186 | I35: 46186 | J35: 0 | K35: Fixed: Changed roundOff default value from false to true in OrderCreateEditPage.tsx initial form state. Commit: 19acc7502
A36: 35 | B36: Sales & Distribution >invoicing | C36: Sales & Distribution >invoicing > -create invoice -In sales invoices ,creating new invoices i have tried to create invoice but I cant and it shows the error message | D36: high | E36: Kalatheeswaran | F36: Gowtham | G36: Unfixed | H36: 46186 | I36: 46186 | J36: =IF(H36="","",TODAY()-H36) -> 1
A37: 36 | B37: Shift Roster | C37: Roster generation does not enforce Factories Act §54 daily 9-hour cap — shifts exceeding 9 hrs are assigned without error | D37: medium | E37: Dhanalakshmi | F37: Dhanalakshmi | G37: Fixed | H37: 46186 | I37: 46186 | J37: =IF(H37="","",TODAY()-H37) -> 1
A38: 37 | B38: Shift Roster | C38: Roster generation does not enforce Factories Act §55 mandatory 30-min break for shifts >5 hours — break_duration_minutes can be 0 on any shift | D38: medium | E38: Dhanalakshmi | F38: Dhanalakshmi | G38: Fixed | H38: 46186 | I38: 46186 | J38: =IF(H38="","",TODAY()-H38) -> 1
A39: 38 | B39: Shift Roster | C39: No spread-of-hours check (Factories Act §56 max 10.5 hrs) — shift start-to-end span is unbounded | D39: medium | E39: Dhanalakshmi | F39: Dhanalakshmi | G39: Fixed | H39: 46186 | I39: 46186 | J39: =IF(H39="","",TODAY()-H39) -> 1
A40: 39 | B40: Shift Roster | C40: min_rest_hours_between_shifts defaults to 0 instead of statutory 11 hrs — shift rotations can be back-to-back if policy row is unconfigured | D40: medium | E40: Dhanalakshmi | F40: Dhanalakshmi | G40: Fixed | H40: 46186 | I40: 46186 | J40: =IF(H40="","",TODAY()-H40) -> 1
A41: 40 | B41: Shift Roster | C41: Roster generator enforces max_headcount upper bound but never blocks assignments below minimum_staffing — understaffed shifts generated silently | D41: medium | E41: Dhanalakshmi | F41: Dhanalakshmi | G41: Fixed | H41: 46186 | I41: 46186 | J41: =IF(H41="","",TODAY()-H41) -> 1
A42: 41 | B42: Shift Roster | C42: No consecutive night shift cap — employees can be assigned unlimited sequential night shifts with no fatigue/safety limit | D42: medium | E42: Dhanalakshmi | F42: Dhanalakshmi | G42: Fixed | H42: 46186 | I42: 46186 | J42: =IF(H42="","",TODAY()-H42) -> 1
A43: 42 | B43: Shift Roster | C43: Quarterly overtime quota (Factories Act §64 max 75 hrs/quarter) not tracked or enforced at assignment or generation level | D43: medium | E43: Dhanalakshmi | F43: Dhanalakshmi | G43: Fixed | H43: 46186 | I43: 46186 | J43: =IF(H43="","",TODAY()-H43) -> 1
A44: 43 | B44: Shift Roster | C44: Blocking §51 day-7 assignment logs an error but does not create a compensatory rest day entitlement as required by Factories Act §52 | D44: medium | E44: Dhanalakshmi | F44: Dhanalakshmi | G44: Fixed | H44: 46186 | I44: 46186 | J44: =IF(H44="","",TODAY()-H44) -> 1
A45: 44 | B45: Shift Roster | C45: Shift validator accepts identical start_time and end_time — zero-duration shifts are not rejected | D45: medium | E45: Dhanalakshmi | F45: Dhanalakshmi | G45: Fixed | H45: 46186 | I45: 46186 | J45: =IF(H45="","",TODAY()-H45) -> 1
A46: 45 | B46: Shift Roster | C46: Shift validator does not reject crosses_midnight=false when end_time < start_time — negative-duration shifts created silently | D46: medium | E46: Dhanalakshmi | F46: Dhanalakshmi | G46: Fixed | H46: 46186 | I46: 46186 | J46: =IF(H46="","",TODAY()-H46) -> 1
A47: 46 | B47: Shift Roster | C47: break_duration_minutes is not compared to shift duration — a break longer than the shift itself is accepted | D47: medium | E47: Dhanalakshmi | F47: Dhanalakshmi | G47: Fixed | H47: 46186 | I47: 46186 | J47: =IF(H47="","",TODAY()-H47) -> 1
... A59: 58 | B59: Shift Roster | C59: Sales & Distribution >invoicing -In sales invoices ,after you click the more option menu and click "Submit for approval" .In there text are not visible in the dark theme | D59: medium | E59: Kalatheeswaran | F59: Gowtham | G59: Unfixed | H59: 46186 | I59: 46186 | J59: =IF(H59="","",TODAY()-H59) -> 1
A60: 59 | B60: Shift Roster | C60: Break times not validated against shift window shiftBreakSchema accepts any start_time/end_time without checking the break falls inside the shift's own start–end window; a break at 14:00 on a 06:00–14:00 shift is accepted. | D60: medium | E60: Dhanalakshmi | F60: Dhanalakshmi | G60: Open | H60: 46186 | I60: 46188 | J60: =IF(H60="","",TODAY()-H60) -> 1 | K60: Shift Roster
A61: 60 | B61: Shift Roster | C61: Multiple breaks not checked for mutual overlap When breaks array has more than one entry, no validation that break intervals don't overlap each other. | D61: medium | E61: Dhanalakshmi | F61: Dhanalakshmi | G61: Open | H61: 46186 | I61: 46188 | J61: =IF(H61="","",TODAY()-H61) -> 1 | K61: Shift Roster
A62: 61 | B62: Shift Roster | C62: Factories Act §54 daily 9-hour cap not in shift validator shiftCrossFieldCheck enforces the 4-hour minimum (GAP-09) but has no ceiling check — a 10-hour or 12-hour shift grossDuration is accepted without error. | D62: medium | E62: Dhanalakshmi | F62: Dhanalakshmi | G62: Open | H62: 46186 | I62: 46188 | J62: =IF(H62="","",TODAY()-H62) -> 1 | K62: Shift Roster
A63: 62 | B63: Shift Roster | C63: Factories Act §55 mandatory 30-min break not enforced in validator Shift duration > 5 hours is accepted with break_duration_minutes: 0 — the statutory 30-minute rest interval is never required by the schema. | D63: medium | E63: Dhanalakshmi | F63: Dhanalakshmi | G63: Open | H63: 46186 | I63: 46188 | J63: =IF(H63="","",TODAY()-H63) -> 1 | K63: Shift Roster
A64: 63 | B64: Shift Roster | C64: Factories Act §56 spread-of-hours ceiling (10.5 h) not checked No validation that end_time − start_time (inclusive of all breaks) stays within the 10.5-hour statutory spread limit | D64: medium | E64: Dhanalakshmi | F64: Dhanalakshmi | G64: Open | H64: 46186 | I64: 46188 | J64: =IF(H64="","",TODAY()-H64) -> 1 | K64: Shift Roster
A65: 64 | B65: Shift Roster | C65: grace_period_minutes and overtime_threshold_minutes not bounded by shift duration Both fields can exceed the shift duration (e.g., OT threshold of 600 min on a 480-min shift means overtime never triggers). No cross-field comparison exists. | D65: medium | E65: Dhanalakshmi | F65: Dhanalakshmi | G65: Open | H65: 46186 | I65: 46188 | J65: =IF(H65="","",TODAY()-H65) -> 1 | K65: Shift Roster
A66: 65 | B66: Shift Roster | C66: Employment type vs assignment type mismatch deferred but never implemented shift-assignment.validator.ts:60 has a comment // Gap 2.4 Note: validated in service layer but the service layer has no such check — a PERMANENT employee can receive a CONTRACTUAL assignment without error. | D66: medium | E66: Dhanalakshmi | F66: Dhanalakshmi | G66: Open | H66: 46186 | I66: 46188 | J66: =IF(H66="","",TODAY()-H66) -> 1 | K66: Shift Roster
A67: 66 | B67: Shift Roster | C67: Shift change request does not verify employee is assigned to from_shift_id on change_date CreateShiftChangeRequestSchema validates the date is not in the past and from ≠ to, but never queries whether the employee actually holds from_shift_id on change_date | D67: medium | E67: Dhanalakshmi | F67: Dhanalakshmi | G67: Open | H67: 46186 | I67: 46188 | J67: =IF(H67="","",TODAY()-H67) -> 1 | K67: Shift Roster
A68: 67 | B68: Shift Roster | C68: Shift swap request does not verify both employees have shifts to swap RequestShiftSwapSchema validates only date and reason — no check that the initiating employee has a shift on change_date or that the swap target has a shift on the same date | D68: medium | E68: Dhanalakshmi | F68: Dhanalakshmi | G68: Open | H68: 46186 | I68: 46188 | J68: =IF(H68="","",TODAY()-H68) -> 1 | K68: Shift Roster
A69: 68 | B69: Shift Roster | C69: WFH request not blocked for night shift workers in manufacturing CreateWFHRequestSchema imposes no restriction on shift type — a night-shift production worker can raise a WFH request, which is operationally invalid in a factory context | D69: medium | E69: Dhanalakshmi | F69: Dhanalakshmi | G69: Open | H69: 46186 | I69: 46188 | J69: =IF(H69="","",TODAY()-H69) -> 1 | K69: Shift Roster
A70: 69 | B70: Shift Roster | C70: STATE holiday type accepted without plant_id CreateHolidaySchema makes plant_id optional for all holiday types, including STATE. A state holiday without plant association applies to no plant specifically and affects all plants globally — a plant_id should be required when holiday_type = 'STATE' | D70: medium | E70: Dhanalakshmi | F70: Dhanalakshmi | G70: Open | H70: 46186 | I70: 46188 | J70: =IF(H70="","",TODAY()-H70) -> 1 | K70: Shift Roster
A71: 70 | B71: Shift Roster | C71: Comp-off credit insert (GAP-08) has no guard for missing 'CO' leave type generateRoster inserts into hr.leave_credits with leave_type_code = 'CO' but never pre-checks that a Compensatory Off leave type exists for the company — the insert will throw a FK violation if the leave type is absent. | D71: medium | E71: Dhanalakshmi | F71: Dhanalakshmi | G71: Open | H71: 46186 | I71: 46188 | J71: =IF(H71="","",TODAY()-H71) -> 1 | K71: Shift Roster
A72: 71 | C72: Quarterly OT cap (Factories Act §64 — 75 hrs/quarter) not tracked No counter or check exists at assignment, generation, or policy level for cumulative overtime per quarter per employee. | D72: medium | J72: =IF(H72="","",TODAY()-H72)
A73: 72 | B73: Sales > Sales Orders > List | C73: Sales > Sales Orders > List > Print — Print Report button was printing the entire order list as one document. Each order should be printable individually from the row action buttons. | D73: low | E73: Ragesh | F73: Thiravidam | G73: Fixed | H73: 46186 | I73: 46186
A74: 73 | B74: sales & Distribution >invoicing | C74: sales & Distribution >invoicing -In sales invoices ,after you click the more option menu and click "Duplicate" then if u save draft the error message it shows is not user friendly | D74: medium | E74: Kalatheeswaran | F74: Gowtham | G74: Unfixed | H74: 46186 | I74: 46186 | J74: =IF(H74="","",TODAY()-H74) -> 1
A75: 74 | B75: sales & Distribution >invoicing | C75: sales & Distribution >invoicing -In sales invoices ,click more option menu and click "preview pdf" and in that if you click download pdf and if you view it the content in the pdf is so small | D75: medium | E75: Kalatheeswaran | F75: Gowtham | G75: Unfixed | H75: 46186 | I75: 46186 | J75: =IF(H75="","",TODAY()-H75) -> 1
A76: 75 | B76: sales & Distribution >invoicing | C76: sales & Distribution >invoicing -In sales invoices , click " ⋮ " and click cancel invoice ,the content in that form is not visible in the dark theme | D76: medium | E76: kalatheeswaran | F76: Gowtham | G76: Unfixed | H76: 46186 | I76: 46186 | J76: =IF(H76="","",TODAY()-H76) -> 1
A77: 76 | B77: sales & Distribution >invoicing | C77: sales & Distribution >invoicing -In sales invoices , click " ⋮ " and click void invoice ,the content in that form is not visible in the dark theme | D77: medium | E77: Kalatheeswaran | F77: Gowtham | G77: Unfixed | H77: 46186 | I77: 46186 | J77: =IF(H77="","",TODAY()-H77) -> 1
A78: 77 | B78: sales & Distribution >invoicing | C78: sales & Distribution >invoicing -In sales invoices , click " ⋮ " and click record payment ,the content are not visible in the dark theme | D78: medium | E78: Kalatheeswaran | F78: Gowtham | G78: Unfixed | H78: 46186 | I78: 46186 | J78: =IF(H78="","",TODAY()-H78) -> 1
A79: 78 | B79: sales & Distribution >invoicing | C79: sales & Distribution >invoicing -In sales invoices , click " ⋮ " and click generate e-invoice ,i cant generate and i tried differnt orders also same error message | D79: medium | E79: Kalatheeswaran | F79: Gowtham | G79: Unfixed | H79: 46186 | I79: 46186 | J79: =IF(H79="","",TODAY()-H79) -> 1
A80: 79 | J80: =IF(H80="","",TODAY()-H80)
A81: 80 | J81: =IF(H81="","",TODAY()-H81)
A82: 81 | J82: =IF(H82="","",TODAY()-H82)
A83: 82 | J83: =IF(H83="","",TODAY()-H83)
A84: 83 | J84: =IF(H84="","",TODAY()-H84)
A85: 84 | J85: =IF(H85="","",TODAY()-H85)
A86: 85 | J86: =IF(H86="","",TODAY()-H86)
A87: 86 | J87: =IF(H87="","",TODAY()-H87)
A88: 87 | J88: =IF(H88="","",TODAY()-H88)
A89: 88 | J89: =IF(H89="","",TODAY()-H89)
A90: 89 | J90: =IF(H90="","",TODAY()-H90)
A91: 90 | J91: =IF(H91="","",TODAY()-H91)
... A194: 193 | J194: =IF(H194="","",TODAY()-H194)

Sheet Test Items Tracker
A1: Test ID | B1: Module | C1: Sub Module | D1: Issue | E1: Description | F1: Tested By | G1: Priority | H1: Status | I1: Owner | J1: Created Date | K1: Target Date | L1: Issue ID
A2: SR-001 | B2: Shift Management | C2: Shift Roster | D2: cycle_week must not exceed cycle_length- | E2: Validator allows cycle_week=5 on a 2-week cycle roster. A shift row that references a week beyond cycle_length will never fire during generation, silently producing an incomplete roster. | F2: Ramamoorthy | G2: High | H2: Closed | I2: Dhanalakshmi | J2: 46185 | K2: 46186
A3: SR-002 | B3: Shift Management | C3: Shift Roster | D3: Block weekly_off_days with all 7 days selected | E3: Validator accepts weekly_off_days=[0,1,2,3,4,5,6]. Generating a roster with all days off produces 0 assignments with no user-visible error. | F3: Ramamoorthy | G3: High | H3: Closed | I3: Dhanalakshmi | J3: 46185 | K3: 46186
A4: SR-003 | B4: Shift Management | C4: Shift Roster | D4: clear_existing misses open-ended assignments | E4: generateRoster with clear_existing=true uses WHERE start_date >= $2 AND start_date <= $3. This misses range-based assignments (end_date IS NULL or beyond range) that cover the generated period. | F4: Ramamoorthy | G4: High | H4: Closed | I4: Dhanalakshmi | J4: 46185 | K4: 46186
A5: SR-004 | B5: Shift Management | C5: Shift Roster | D5: Cross-tenant data leak in getRosterByDate | E5: getRosterByDate filters by plantId/departmentId without scoping to company_id. A request with a valid UUID from another company's plant can return that tenant's employee roster. | F5: Ramamoorthy | G5: High | H5: Closed | I5: Dhanalakshmi | J5: 46185 | K5: 46186
A6: SR-005 | B6: Shift Management | C6: Shift Roster | D6: Generation error list not surfaced in UI | E6: API returns errors[] array (employee ID, date, reason per entry) but the UI only shows a single count toast. Users cannot identify which employees or dates failed without checking logs. | F6: Ramamoorthy | G6: High | H6: Closed | I6: Dhanalakshmi | J6: 46185 | K6: 46186
A7: SR-006 | B7: Shift Management | C7: Shift Roster | D7: ROTATING template accepts fewer shifts than cycle_length | E7: A 3-week ROTATING cycle can be saved with shift rows only for week 1. Weeks 2 and 3 silently get no assignments during generation — no warning shown to user. | F7: Ramamoorthy | G7: High | H7: Closed | I7: Dhanalakshmi | J7: 46185 | K7: 46186
A8: SR-007 | B8: Shift Management | C8: Shift Roster | D8: Submit button not disabled when no valid shifts in template form | E8: Handler checks valid.length === 0 after submit and shows toast, but the Create/Update button remains enabled. API rejects it anyway, but UX is confusing and wastes a network round-trip. | F8: Ramamoorthy | G8: High | H8: Closed | I8: Dhanalakshmi | J8: 46185 | K8: 46186
A9: SR-008 | B9: Shift Management | C9: Shift Roster | D9: display_order not re-sequenced after row removal in DAY_CYCLE | E9: addRow() sets displayOrder=prev.length+1 correctly, but removeRow() leaves gaps (e.g. [1,2,4] after removing index 2). DAY_CYCLE rotation depends on display_order for correct sequence. | F9: Ramamoorthy | G9: High | H9: Closed | I9: Dhanalakshmi | J9: 46185 | K9: 46186
A10: SR-009 | B10: Shift Management | C10: Shift Roster | D10: shift_id existence not verified before saving template | E10: Validator accepts any valid UUID as shift_id. If the UUID references a deleted or wrong-company shift, the roster detail row is inserted with an orphaned FK — future generation silently skips those rows. | F10: Ramamoorthy | G10: High | H10: Closed | I10: Dhanalakshmi | J10: 46185 | K10: 46186
A11: SR-010 | B11: Shift Management | C11: Shift Roster | D11: Shift capacity hardcoded to 999 in getShiftAvailability | E11: getRosterAvailability returns available_capacity: 999 (hardcoded placeholder). No warning is issued when a shift is over-staffed during generation or manual assignment. | F11: Ramamoorthy | G11: High | H11: Closed | I11: Dhanalakshmi | J11: 46185 | K11: 46186
A12: SR-011 | B12: Shift Management | C12: Shift Roster | D12: No 6-day/week max enforcement during roster generation | E12: generateRoster does not count assigned days per employee per calendar week. India Factories Act §51 limits work to 6 days/week. Over-assignment is written to DB without warning. | F12: Ramamoorthy | G12: High | H12: Closed | I12: Dhanalakshmi | J12: 46185 | K12: 46186
A13: SR-012 | B13: Shift Management | C13: Shift Roster | D13: No minimum rest-hours check between consecutive shifts | E13: generateRoster does not verify that the gap between an employee's previous shift end time and the new shift start time meets hr.shift_policies.min_rest_hours_between_shifts. This can create legally non-compliant schedules. | F13: Ramamoorthy | G13: High | H13: Closed | I13: Dhanalakshmi | J13: 46185 | K13: 46186
... A24: HR-SE-002 | B24: Separation& Exit | C24: F& F settlements | D24: column e.is_pf_applicable does not exist | E24: column e.is_pf_applicable does not exist -error while review F & F Settlements-http://localhost:3001/en/hr/separation/fnf | F24: Ramamoorthy | G24: Medium | H24: Closed | I24: Dhanalakshmi | J24: 46185 | K24: 46187
A25: INV-001 | B25: Inventory | C25: Material Request | E25: UI/UX testing, Logical testing, Data accuracy testing | F25: Manjunath | G25: High | H25: Closed | I25: Thiravidam | J25: 46185 | K25: 46185
A26: INV-002 | B26: Inventory | C26: Material Issues | E26: UI/UX testing, Logical testing, Data accuracy testing | F26: Manjunath | G26: High | H26: Closed | I26: Thiravidam | J26: 46185 | K26: 46185
A27: INV-003 | B27: Inventory | C27: Material Issue Reports | E27: UI/UX testing, Logical testing, Data accuracy testing | F27: Manjunath | G27: High | H27: Closed | I27: Thiravidam | J27: 46185 | K27: 46185
A28: INV-004 | B28: Inventory | C28: Material Returns | E28: UI/UX testing, Logical testing, Data accuracy testing | F28: Manjunath | G28: High | H28: Closed | I28: Thiravidam | J28: 46185 | K28: 46185
A29: INV-005 | B29: Inventory | C29: Stock Transactions > Finished Goods Entry | E29: UI/UX testing, Logical testing, Data accuracy testing | F29: Manjunath | G29: High | H29: Closed | I29: Gowtham | J29: 46185 | K29: 46185
A30: SO-001 | B30: Sales & Distribution | C30: Sales Order > order list | E30: UI/UX testing, Logical testing, Data accuracy testing | F30: Manjunath | G30: High | H30: Closed | I30: Gowtham | J30: 46185 | K30: 46185
A31: SO-002 | B31: Sales & Distribution | C31: Sales Order > Dispatch Orders | D31: give an waring message like please enter driver details to enable start loading option | E31: UI/UX testing, Logical testing, Data accuracy testing | F31: Manjunath | G31: High | H31: Closed | I31: Gowtham | J31: 46185 | K31: 46185 | L31: 30
A32: SO-003 | B32: Sales & Distribution | C32: Invocing | E32: UI/UX testing, Logical testing, Data accuracy testing | F32: Manjunath | G32: High | H32: Closed | I32: Gowtham | J32: 46185 | K32: 46185
A33: HR-SE-001 | B33: HR management | C33: Separation Dashboard | D33: Initiate Separation button not requried in Separation Dashboard | E33: UI/UX testing | F33: Manjunath | G33: High | H33: Closed | I33: Dhanalakshmi | J33: 46186 | K33: 46186
A34: HR-SE-002 | B34: HR management | C34: Full & Final Settlement | D34: Full & Final Settlement Detail while calucalting total debits is zero | E34: UI/UX testing, Logical testing, Data accuracy testing | F34: Manjunath | G34: High | H34: open | I34: Dhanalakshmi | J34: 46186 | K34: 46186
A35: HR-SE-003 | B35: HR management | C35: Full & Final Settlement | D35: Full & Final Settlement Detail i have edited Advance recovery now credits and everything is zero | E35: UI/UX testing, Logical testing, Data accuracy testing | F35: Manjunath | G35: High | H35: open | I35: Dhanalakshmi | J35: 46186 | K35: 46186
A36: HR-SE-004 | B36: HR management | C36: Full & Final Settlement | D36: while viewing the payslip this error comes column sr.notice_shortfall_deduction does not exist | E36: UI/UX testing, Logical testing, Data accuracy testing | F36: Manjunath | G36: High | H36: open | I36: Dhanalakshmi | J36: 46186 | K36: 46186
A37: HR-SE-005 | B37: HR management | C37: Exit Interview | D37: Conduct Interview Satisfaction Ratings toggles button is not visable both in dark and light mode | E37: UI/UX testing | F37: Manjunath | G37: High | H37: open | I37: Dhanalakshmi | J37: 46186 | K37: 46186
A38: HR-SE-006 | B38: HR management | C38: Separation Request | D38: gratuity button -Dashboard Error | E38: UI/UX testing | F38: Dhanalakshmi | G38: High | H38: open | I38: Dhanalakshmi | J38: 46186 | K38: 46186
A39: HR-SE-007 | B39: HR management | C39: Separation Documents | D39: while genrating document PDF generation service not yet implemented | E39: UI/UX testing, Logical testing | F39: Manjunath | G39: High | H39: Closed | I39: Dhanalakshmi | J39: 46186 | K39: 46186
E44: In sales invoices , click " ⋮ "
A45: SD-INV-001 | B45: Sales & Distribution | C45: Invocing | D45: Theme Issue in the sales invoices | E45: In sales invoices ,generate from SO ,the text are not visible in the dark theme | F45: Kalatheeswaran | G45: High | H45: Open | I45: Gowtham | J45: 46186 | K45: 46186 | L45: 31
A46: SD-INV-002 | B46: sales & Distribution | C46: Invocing | D46: Line item 1: HSN code 2833 not found in current schedule | E46: In sales invoices ,creating new invoices i have tried to create invoice but I cant and it shows the error message | F46: Kalatheeswaran | G46: High | H46: open | I46: Gowtham | J46: 46186 | K46: 46186 | L46: 35
A47: SD-INV-003 | B47: Sales & Distribution | C47: Invocing | D47: Theme Issue in the sales invoices | E47: In sales invoices ,after you click the more option menu and click "Submit for approval" .In there text are not visible in the dark theme | F47: Kalatheeswaran | G47: Medium | H47: open | I47: Gowtham | J47: 46186 | K47: 46186 | L47: 58
A48: SD-INV-004 | B48: Sales & Distribution | C48: Invocing | D48: new row for relation "invoices" violates check constraint "chk_invoice_grand_total" | E48: In sales invoices ,after you click the more option menu and click "Duplicate" then if u save draft the error message it shows is not user friendly | F48: Kalatheeswaran | G48: High | H48: open | I48: Gowtham | J48: 46186 | K48: 46186 | L48: 73
A49: SD-INV-005 | B49: Sales & Distribution | C49: Invocing | D49: Content in PDF are not visible | E49: In sales invoices ,click more option menu and click "preview pdf" and in that if you click download pdf and if you view it the content in the pdf is so small | F49: Kalatheeswaran | G49: Medium | H49: open | I49: Gowtham | J49: 46186 | K49: 46186 | L49: 74
A50: SD-INV-006 | B50: Sales & Distribution | C50: Invocing | D50: theme Issue in the sales invoices | E50: In sales invoices , click " ⋮ " and click cancel invoice ,the content in that form is not visible in the dark theme | F50: Kalatheeswaran | G50: Medium | H50: open | I50: Gowtham | J50: 46186 | K50: 46186 | L50: 75
A51: SD-INV-007 | B51: Sales & Distribution | C51: Invocing | D51: Theme Issue in the sales invoices | E51: In sales invoices , click " ⋮ " and click void invoice ,the content are not visible in the dark theme | F51: Kalatheeswaran | G51: Medium | H51: open | I51: Gowtham | J51: 46186 | K51: 46186 | L51: 76
A52: SD-INV-008 | B52: Sales & Distribution | C52: Invocing | D52: Theme Issue in the sales invoices | E52: In sales invoices , click " ⋮ " and click record payment ,the content are not visible in the dark theme | F52: Kalatheeswaran | G52: Medium | H52: open | I52: Gowtham | J52: 46186 | K52: 46186 | L52: 77
A53: SD-INV-009 | B53: Sales & Distribution | C53: Invocing | D53: Error message "Action failed. Please try again." | E53: In sales invoices , click " ⋮ " and click generate e-invoice ,i cant generate and i tried differnt orders also same error message | F53: Kalatheeswaran | G53: Medium | H53: open | I53: Gowtham | J53: 46186 | K53: 46186 | L53: 78

Sheet Sprint Tracker
A1: Sprint | B1: Start Date | C1: End Date | D1: Planned Stories | E1: Completed Stories | F1: Velocity % | G1: Sprint Status
F2: =IF(D2=0,"",E2/D2)
F3: =IF(D3=0,"",E3/D3)
F4: =IF(D4=0,"",E4/D4)
F5: =IF(D5=0,"",E5/D5)
F6: =IF(D6=0,"",E6/D6)
F7: =IF(D7=0,"",E7/D7)
F8: =IF(D8=0,"",E8/D8)
F9: =IF(D9=0,"",E9/D9)
F10: =IF(D10=0,"",E10/D10)
F11: =IF(D11=0,"",E11/D11)
F12: =IF(D12=0,"",E12/D12)
F13: =IF(D13=0,"",E13/D13)
... F201: =IF(D201=0,"",E201/D201)

Sheet Dashboard
A1: Metric | B1: Value
A2: Total Requirements | B2: =COUNTA('Requirements Tracker'!A:A)-1 -> 81
A3: Open Requirements | B3: =COUNTIF('Requirements Tracker'!F:F,"<>Completed")-1 -> 1048575
A4: Total Issues | B4: =COUNTA('Issue Tracker'!A:A)-1 -> 193
A5: Open Issues | B5: =COUNTIF('Issue Tracker'!G:G,"Open") -> 12
A6: Overdue RAID Items | B6: =COUNTIFS('Action Item'!E:E,"<"&TODAY(),'Action Item'!F:F,"<>Completed") -> 0
A7: Average Sprint Velocity | B7: =AVERAGE('Sprint Tracker'!F:F) -> #DIV/0!

Sheet Support
A1: ID | B1: Customer | C1: Product | D1: Requirement | E1: Requestor | F1: Priority | G1: Status | H1: Owner | I1: Created Date | J1: Target Date | K1: Actual Completion | L1: Remarks
A2: 1 | B2: NR Agarwal | C2: Optrim Web | D2: 2FA feature in Optrim login | E2: NR Agarwal | F2: Medium | G2: Inprogress | H2: Prabahar | I2: 46184 | J2: 46186 | L2: Should able to support AWS and on-premise hosting
A3: 2 | B3: KAPA Papaer - SriLanka | C3: Optrim Web | D3: Trial Initiated | E3: Netique | F3: High | G3: Completed | H3: Prabahar | I3: 46186 | J3: 46186 | K3: 46186
A4: 3 | B4: Mr.Subbiah | C4: Health Tracker | D4: Deploy in server | E4: Thiravidam | F4: Medium | G4: Completed | H4: Kalatheeswaran | I4: 46185 | J4: 46185 | K4: 46185 | L4: need to host tunnel
A5: 4 | B5: Lemit Paper Mill | C5: BPApp version 0.1 | D5: Rewinder Process- Produced Set was missing | E5: Piyush | F5: High | G5: Completed | H5: Thiravidam | I5: 46185 | J5: 46185 | K5: 46185

Sheet Action Item
A1: ID | B1: Type | C1: Description | D1: Owner | E1: Due Date | F1: Status
